scrapeswa/__init__.py
scrapeswa/scrapeswa.py
scrapeswa/util.py
scrapeswa-0.0.4.dist-info/LICENSE
scrapeswa-0.0.4.dist-info/METADATA
scrapeswa-0.0.4.dist-info/WHEEL
scrapeswa-0.0.4.dist-info/top_level.txt
scrapeswa-0.0.4.dist-info/RECORD
